layeredconfig/dictsource.py
layeredconfig/layeredconfig.py
layeredconfig/etcdstore.py
layeredconfig/inifile.py
layeredconfig/plistfile.py
layeredconfig/__init__.py
layeredconfig/commandline.py
layeredconfig/pyfile.py
layeredconfig/jsonfile.py
layeredconfig/yamlfile.py
layeredconfig/environment.py
layeredconfig/defaults.py
layeredconfig/configsource.py
layeredconfig-0.3.3.dist-info/RECORD
layeredconfig-0.3.3.dist-info/metadata.json
layeredconfig-0.3.3.dist-info/WHEEL
layeredconfig-0.3.3.dist-info/DESCRIPTION.rst
layeredconfig-0.3.3.dist-info/top_level.txt
layeredconfig-0.3.3.dist-info/METADATA
