Metadata-Version: 2.0
Name: layeredconfig
Version: 0.3.3
Summary: Manages configuration coming from config files, environment variables, command line arguments, code defaults or other sources
Home-page: https://github.com/staffanm/layeredconfig
Author: Staffan Malmgren
Author-email: staffan.malmgren@gmail.com
License: BSD
Keywords: configuration
Platform: UNKNOWN
Classifier: Development Status :: 3 - Alpha
Classifier: Intended Audience :: Developers
Classifier: License :: OSI Approved :: BSD License
Classifier: Natural Language :: English
Classifier: Programming Language :: Python :: 2
Classifier: Programming Language :: Python :: 2.6
Classifier: Programming Language :: Python :: 2.7
Classifier: Programming Language :: Python :: 3
Classifier: Programming Language :: Python :: 3.3
Classifier: Programming Language :: Python :: 3.4
Classifier: Programming Language :: Python :: 3.5
Requires-Dist: six
Requires-Dist: PyYAML
Requires-Dist: requests
